seqsynch/__init__.py
seqsynch/agent.py
seqsynch/command_line.py
seqsynch/config.py
seqsynch-0.3.dist-info/METADATA
seqsynch-0.3.dist-info/RECORD
seqsynch-0.3.dist-info/WHEEL
seqsynch-0.3.dist-info/entry_points.txt
seqsynch-0.3.dist-info/top_level.txt
