Metadata-Version: 2.1
Name: seqsynch
Version: 0.3
Summary: GitHub synch for sequence management
Home-page: https://github.com/medneo/protocol_management_github_ssh
Author: David Mezey (mezdahun) @ Medneo
Author-email: david.mezey@medneo.com
License: UNKNOWN
Platform: UNKNOWN
Requires-Dist: schedule
Requires-Dist: gitpython
Requires-Dist: configparser
